autotranslate/__init__.py
autotranslate/compat.py
autotranslate/models.py
autotranslate/services.py
autotranslate/utils.py
autotranslate/management/__init__.py
autotranslate/management/commands/__init__.py
autotranslate/management/commands/translate_messages.py
autotranslate/tests/__init__.py
autotranslate/tests/test_translate_messages.py
django_autotranslate-1.3.0.dist-info/LICENSE
django_autotranslate-1.3.0.dist-info/METADATA
django_autotranslate-1.3.0.dist-info/WHEEL
django_autotranslate-1.3.0.dist-info/top_level.txt
django_autotranslate-1.3.0.dist-info/RECORD
