Metadata-Version: 2.1
Name: django-autotranslate
Version: 1.3.0
Summary: A simple Django app to automatically translate the pot (`.po`) files generated by django's makemessages command using google translate.
Home-page: https://github.com/ankitpopli1891/django-autotranslate/
Author: Ankit Popli
Author-email: ankitpopli1891@gmail.com
License: MIT License
Classifier: Environment :: Web Environment
Classifier: Framework :: Django
Classifier: Development Status :: 5 - Production/Stable
Classifier: Intended Audience :: Developers
Classifier: License :: OSI Approved :: MIT License
Classifier: Natural Language :: English
Classifier: Programming Language :: Python
Classifier: Programming Language :: Python :: 3
Classifier: Topic :: Internet :: WWW/HTTP
Classifier: Topic :: Internet :: WWW/HTTP :: Dynamic Content
Classifier: Topic :: Software Development :: Libraries :: Python Modules
License-File: LICENSE
Requires-Dist: django
Requires-Dist: goslate
Requires-Dist: polib
Requires-Dist: six
